token_itemize/__init__.py
token_itemize/cache.py
token_itemize/cli.py
token_itemize/config.py
token_itemize/main.py
token_itemize/styles.py
token_itemize/utils.py
token_itemize/api/__init__.py
token_itemize/api/api_client.py
token_itemize/api/conversation_saver.py
token_itemize/assets/logo.png
token_itemize/gui/__init__.py
token_itemize/gui/gui_app.py
token_itemize/tokenizers/__init__.py
token_itemize/tokenizers/audio_tokenizer.py
token_itemize/tokenizers/image_tokenizer.py
token_itemize/tokenizers/text_tokenizer.py
token_itemize/tokenizers/video_tokenizer.py
token_itemize-1.0.0.dist-info/licenses/LICENSE
token_itemize-1.0.0.dist-info/METADATA
token_itemize-1.0.0.dist-info/WHEEL
token_itemize-1.0.0.dist-info/entry_points.txt
token_itemize-1.0.0.dist-info/top_level.txt
token_itemize-1.0.0.dist-info/RECORD
