Metadata-Version: 2.4
Name: token-itemize
Version: 1.0.0
Summary: A package to count tokens for various file types with API integration.
Author-email: Benevolence Messiah <benevolence.messiah@gmail.com>
License-Expression: MIT
Project-URL: Homepage, https://github.com/BenevolenceMessiah/token-itemize
Project-URL: Documentation, https://github.com/BenevolenceMessiah/token-itemize#readme
Project-URL: Issues, https://github.com/BenevolenceMessiah/token-itemize/issues
Project-URL: Changelog, https://github.com/BenevolenceMessiah/token-itemize/releases
Classifier: Programming Language :: Python :: 3
Classifier: Operating System :: OS Independent
Requires-Python: >=3.8
License-File: LICENSE
Requires-Dist: setuptools>=65.5.0
Requires-Dist: wheel>=0.45.1
Requires-Dist: twine>=6.1.0
Requires-Dist: build>=1.2.2.post1
Requires-Dist: Pillow>=11.1.0
Requires-Dist: tiktoken>=0.9.0
Requires-Dist: requests>=2.32.3
Requires-Dist: numpy>=2.2.3
Requires-Dist: PyYAML>=6.0.2
Requires-Dist: opencv-python>=4.11.0.86
Requires-Dist: PyQt5>=5.15.11
Requires-Dist: pathspec>=0.12.1
Requires-Dist: openai>=1.66.3
Provides-Extra: dev
Requires-Dist: pytest>=7.0; extra == "dev"
Requires-Dist: coverage>=6.0; extra == "dev"
Dynamic: license-file
